lithikos/Scale.py
lithikos/__init__.py
lithikos/__main__.py
lithikos/_sample.py
lithikos/analysis.py
lithikos/analysis_method.py
lithikos/artefact_analysis.py
lithikos/artefact_info.py
lithikos/artefact_segments.py
lithikos/construction.py
lithikos/construction_data.py
lithikos/contructed_result.py
lithikos/exceptions.py
lithikos/measurement_data.py
lithikos/orientation.py
lithikos/orientation_method.py
lithikos/plotting.py
lithikos/process.py
lithikos/quadrant_data.py
lithikos/quadrant_measurements.py
lithikos/sample_parameters.py
lithikos/sampling.py
lithikos/slice_data.py
lithikos/utils.py
lithikos/configs/__init__.py
lithikos/configs/stderr-file.yaml
lithikos/templates/__init__.py
lithikos/templates/sample_output.html
lithikos/templates/sample_output.txt
lithikos-0.0.12.dist-info/METADATA
lithikos-0.0.12.dist-info/WHEEL
lithikos-0.0.12.dist-info/entry_points.txt
lithikos-0.0.12.dist-info/top_level.txt
lithikos-0.0.12.dist-info/RECORD
