Metadata-Version: 2.4
Name: lithikos
Version: 0.0.12
Summary: A package supporting analysis of stone tools.
Author-email: Graham James Addis <graham@addis.org.uk>, James Hicks <james.hicks@arch.ox.ac.uk>
Project-URL: Homepage, https://gitlab.com/lithikos/lithikos
Project-URL: Issues, https://gitlab.com/lithikos/lithikos/issues
Classifier: Development Status :: 1 - Planning
Classifier: Programming Language :: Python :: 3
Classifier: License :: OSI Approved :: Apache Software License
Classifier: Operating System :: OS Independent
Requires-Python: >=3.10
Requires-Dist: scipy==1.15.2
Requires-Dist: matplotlib==3.10.1
Requires-Dist: vedo==2025.5.3
Requires-Dist: vtk==9.4.1
Requires-Dist: treelib==1.7.1
Requires-Dist: pandas==2.2.3
Requires-Dist: tqdm==4.67.1
Requires-Dist: pyyaml==6.0.2
Requires-Dist: trimesh==4.6.5
Requires-Dist: filelock==3.18.0
Requires-Dist: jinja2==3.1.6
